dynaperms/__init__.py
dynaperms/apps.py
dynaperms/backends.py
dynaperms/utils.py
dynaperms-0.1.0.dist-info/LICENSE
dynaperms-0.1.0.dist-info/WHEEL
dynaperms-0.1.0.dist-info/METADATA
dynaperms-0.1.0.dist-info/RECORD
